organizze_api/__init__.py
organizze_api/api_client.py
organizze_api/api_response.py
organizze_api/configuration.py
organizze_api/exceptions.py
organizze_api/py.typed
organizze_api/rest.py
organizze_api/api/__init__.py
organizze_api/api/bank_accounts_api.py
organizze_api/api/budgets_api.py
organizze_api/api/categories_api.py
organizze_api/api/credit_cards_api.py
organizze_api/api/transactions_api.py
organizze_api/api/users_api.py
organizze_api/models/__init__.py
organizze_api/models/bank_account.py
organizze_api/models/bank_account_input.py
organizze_api/models/budget.py
organizze_api/models/category.py
organizze_api/models/category_input.py
organizze_api/models/create_transaction_request.py
organizze_api/models/credit_card.py
organizze_api/models/credit_card_input.py
organizze_api/models/credit_card_invoice.py
organizze_api/models/credit_card_invoice_full.py
organizze_api/models/delete_transaction_request.py
organizze_api/models/failed_authentication.py
organizze_api/models/installment_transaction.py
organizze_api/models/installment_transaction_all_of_installments_attributes.py
organizze_api/models/not_found.py
organizze_api/models/recurring_transaction.py
organizze_api/models/recurring_transaction_all_of_recurrence_attributes.py
organizze_api/models/tag.py
organizze_api/models/transaction.py
organizze_api/models/transaction_input.py
organizze_api/models/update_transaction_request.py
organizze_api/models/user.py
organizze_api/models/validation_error.py
organizze_api-1.0.6.dist-info/licenses/LICENSE
organizze_api-1.0.6.dist-info/METADATA
organizze_api-1.0.6.dist-info/WHEEL
organizze_api-1.0.6.dist-info/top_level.txt
organizze_api-1.0.6.dist-info/RECORD
