Metadata-Version: 2.4
Name: organizze_api
Version: 1.0.6
Summary: SDK to interface with the Organizze REST API
Home-page: https://pypi.org/project/organizze_api/
Author: Rhuan Barreto
Author-email: Rhuan Barreto <rhuan@barreto.work>
License-Expression: Apache-2.0
Project-URL: Repository, https://github.com/BarretoTech/organizze-api-sdk
Keywords: OpenAPI,OpenAPI-Generator,Organizze
Classifier: Development Status :: 5 - Production/Stable
Classifier: Intended Audience :: Developers
Classifier: Programming Language :: Python :: 3
Classifier: Topic :: Office/Business :: Financial
Requires-Python: >=3.9
License-File: LICENSE
Requires-Dist: urllib3<3.0.0,>=2.1.0
Requires-Dist: python-dateutil>=2.8.2
Requires-Dist: pydantic>=2
Requires-Dist: typing-extensions>=4.7.1
Dynamic: author
Dynamic: home-page
Dynamic: license-file
